sier2/__init__.py
sier2/__main__.py
sier2/_block.py
sier2/_config.py
sier2/_dag.py
sier2/_library.py
sier2/_logger.py
sier2/_util.py
sier2/_version.py
sier2/panel/__init__.py
sier2/panel/_chart.py
sier2/panel/_feedlogger.py
sier2/panel/_panel.py
sier2/panel/_panel_util.py
sier2-1.0.1.dist-info/METADATA
sier2-1.0.1.dist-info/WHEEL
sier2-1.0.1.dist-info/licenses/LICENSE
sier2-1.0.1.dist-info/RECORD
