Metadata-Version: 2.4
Name: sier2
Version: 1.0.1
Summary: Blocks of code that are executed in dags
License-File: LICENSE
Author: Algol60
Author-email: algol60 <algol60@users.noreply.github.com>
Classifier: Programming Language :: Python :: 3.11
Classifier: Programming Language :: Python :: 3.12
Classifier: License :: OSI Approved :: MIT License
Classifier: Operating System :: OS Independent
Classifier: Intended Audience :: Science/Research
Classifier: Intended Audience :: Developers
Classifier: Topic :: Scientific/Engineering
Classifier: Topic :: Software Development :: Libraries
Project-URL: Homepage, https://github.com/sier2/sier2
